semantic_digital_twin/__init__.py
semantic_digital_twin/exceptions.py
semantic_digital_twin/testing.py
semantic_digital_twin/utils.py
semantic_digital_twin/world.py
semantic_digital_twin/adapters/__init__.py
semantic_digital_twin/adapters/fbx.py
semantic_digital_twin/adapters/mesh.py
semantic_digital_twin/adapters/mjcf.py
semantic_digital_twin/adapters/multi_parser.py
semantic_digital_twin/adapters/urdf.py
semantic_digital_twin/adapters/usd.py
semantic_digital_twin/adapters/viz_marker.py
semantic_digital_twin/adapters/procthor/__init__.py
semantic_digital_twin/adapters/procthor/procthor_parser.py
semantic_digital_twin/adapters/procthor/procthor_pipelines.py
semantic_digital_twin/adapters/ros/__init__.py
semantic_digital_twin/adapters/ros/messages.py
semantic_digital_twin/adapters/ros/world_fetcher.py
semantic_digital_twin/adapters/ros/world_synchronizer.py
semantic_digital_twin/callbacks/__init__.py
semantic_digital_twin/callbacks/callback.py
semantic_digital_twin/collision_checking/__init__.py
semantic_digital_twin/collision_checking/collision_detector.py
semantic_digital_twin/collision_checking/trimesh_collision_detector.py
semantic_digital_twin/datastructures/__init__.py
semantic_digital_twin/datastructures/prefixed_name.py
semantic_digital_twin/datastructures/types.py
semantic_digital_twin/datastructures/variables.py
semantic_digital_twin/orm/__init__.py
semantic_digital_twin/orm/model.py
semantic_digital_twin/orm/ormatic_interface.py
semantic_digital_twin/orm/utils.py
semantic_digital_twin/pipeline/__init__.py
semantic_digital_twin/pipeline/mesh_decomposer.py
semantic_digital_twin/pipeline/pipeline.py
semantic_digital_twin/reasoning/__init__.py
semantic_digital_twin/reasoning/predicates.py
semantic_digital_twin/reasoning/reasoner.py
semantic_digital_twin/reasoning/robot_predicates.py
semantic_digital_twin/reasoning/world_reasoner.py
semantic_digital_twin/reasoning/world_rdr/__init__.py
semantic_digital_twin/reasoning/world_rdr/world_rdr.py
semantic_digital_twin-0.0.5.dist-info/licenses/LICENSE
semantic_digital_twin-0.0.5.dist-info/METADATA
semantic_digital_twin-0.0.5.dist-info/WHEEL
semantic_digital_twin-0.0.5.dist-info/top_level.txt
semantic_digital_twin-0.0.5.dist-info/RECORD
