Metadata-Version: 2.4
Name: semantic_digital_twin
Version: 0.0.5
Summary: A world model that unifies kinematic information and semantic meaning for robotic world representations.
Author-email: Tom Schierenbeck <tom_sch@uni-bremen.de>
License: LGPL-3.0-only
Project-URL: Source, https://github.com/cram2/semantic_digital_twin
Project-URL: Bug Tracker, https://github.com/cram2/semantic_digital_twin/issues
Keywords: robotics
Classifier: Programming Language :: Python :: 3
Classifier: License :: OSI Approved :: GNU General Public License v3 (GPLv3)
Classifier: Operating System :: OS Independent
Requires-Python: >=3.10
License-File: LICENSE
Requires-Dist: rustworkx
Requires-Dist: numpy
Requires-Dist: trimesh
Requires-Dist: typing_extensions
Requires-Dist: urdf-parser-py
Requires-Dist: matplotlib
Requires-Dist: casadi~=3.7.0
Requires-Dist: hypothesis
Requires-Dist: pytest
Requires-Dist: scipy
Requires-Dist: sqlacodegen
Requires-Dist: ripple_down_rules>=0.6.51
Requires-Dist: pytest-order
Requires-Dist: sqlalchemy
Requires-Dist: embreex
Requires-Dist: rtree
Requires-Dist: random_events
Requires-Dist: plotly
Requires-Dist: rtree
Requires-Dist: daqp
Requires-Dist: pathlib
Requires-Dist: probabilistic_model
Requires-Dist: python-fcl
Requires-Dist: manifold3d
Requires-Dist: krrood==1.1.1
Requires-Dist: rustworkx_utils
Requires-Dist: polytope
Requires-Dist: ortools
Requires-Dist: fbxloader
Requires-Dist: coacd
Requires-Dist: pymysql
Requires-Dist: pyglet==1.5.31
Requires-Dist: pycollada
Provides-Extra: gui
Requires-Dist: ripple_down_rules[gui]; extra == "gui"
Dynamic: license-file
